py_wifi_helper/__init__.py
py_wifi_helper/cli_permission.py
py_wifi_helper/cmd.py
py_wifi_helper/config.py
py_wifi_helper/macos_app_generator.py
py_wifi_helper/macos_wifi_permission_helper.py
py_wifi_helper/my_macos_helper.py
py_wifi_helper/my_macos_helper_v1.py
py_wifi_helper/my_macos_helper_v2.py
py_wifi_helper/my_ubuntu_helper.py
py_wifi_helper/my_windows_helper.py
py_wifi_helper/universal_app_generator.py
py_wifi_helper/yy_wifi_helper.py
py_wifi_helper-2.0.4.dist-info/licenses/LICENSE
py_wifi_helper-2.0.4.dist-info/METADATA
py_wifi_helper-2.0.4.dist-info/WHEEL
py_wifi_helper-2.0.4.dist-info/entry_points.txt
py_wifi_helper-2.0.4.dist-info/top_level.txt
py_wifi_helper-2.0.4.dist-info/RECORD
