Metadata-Version: 2.4
Name: py-wifi-helper
Version: 2.0.4
Summary: A cross-platform WiFi management tool for Windows, macOS, and Ubuntu
Home-page: https://github.com/changyy/py-wifi-helper
Download-URL: https://pypi.org/project/py-wifi-helper/
Author: Yuan-Yi Chang
Author-email: <changyy.csie@gmail.com>
Keywords: python,wifi,interface,macos,ubuntu,windows,network,wireless
Classifier: Development Status :: 5 - Production/Stable
Classifier: Environment :: Console
Classifier: Intended Audience :: Developers
Classifier: Intended Audience :: System Administrators
Classifier: Programming Language :: Python :: 3
Classifier: Programming Language :: Python :: 3.10
Classifier: Operating System :: MacOS :: MacOS X
Classifier: Operating System :: Microsoft :: Windows :: Windows 10
Classifier: Operating System :: Microsoft :: Windows :: Windows 11
Classifier: Operating System :: POSIX :: Linux
Classifier: Topic :: System :: Networking
Classifier: Topic :: Utilities
Requires-Python: >=3.10
License-File: LICENSE
Requires-Dist: pyobjc-core>=10.3; platform_system == "Darwin"
Requires-Dist: pyobjc-framework-Cocoa>=10.3; platform_system == "Darwin"
Requires-Dist: pyobjc-framework-CoreWLAN>=10.3; platform_system == "Darwin"
Requires-Dist: pywifi>=1.1.12; platform_system == "Windows"
Requires-Dist: comtypes>=1.2.0; platform_system == "Windows"
Dynamic: author
Dynamic: author-email
Dynamic: classifier
Dynamic: description
Dynamic: description-content-type
Dynamic: download-url
Dynamic: home-page
Dynamic: keywords
Dynamic: license-file
Dynamic: requires-dist
Dynamic: requires-python
Dynamic: summary
